setup.py
buglib/__init__.py
buglib/bug_test.py
buglib/bugcatcher.py
buglib.egg-info/PKG-INFO
buglib.egg-info/SOURCES.txt
buglib.egg-info/dependency_links.txt
buglib.egg-info/top_level.txt