Metadata-Version: 1.0
Name: buglib
Version: 0.7.0
Summary: Collect traceback to file or server
Home-page: http://www.tdace.com
Author: zhangligang
Author-email: 394452216@qq.com
License: UNKNOWN
Platform: UNKNOWN
